kcwcache
