Metadata-Version: 1.2
Name: kcwcache
Version: 3.33
Summary: kcwcache
Home-page: UNKNOWN
Author: 百里
Author-email: kcwebs@kwebapp.cn
Maintainer: 坤坤
Maintainer-email: fk1402936534@qq.com
License: MIT License
Keywords: kcwcache3.33
Platform: UNKNOWN
